odoo10_addon_github_connector-10.0.1.0.0.99.dev25-py2.7-nspkg.pth
odoo/addons/github_connector/README.rst
odoo/addons/github_connector/__init__.py
odoo/addons/github_connector/__openerp__.py
odoo/addons/github_connector/data/ir_config_parameter.xml
odoo/addons/github_connector/data/ir_cron.xml
odoo/addons/github_connector/demo/github_organization.xml
odoo/addons/github_connector/demo/github_organization_serie.xml
odoo/addons/github_connector/demo/res_groups.xml
odoo/addons/github_connector/models/__init__.py
odoo/addons/github_connector/models/abstract_github_model.py
odoo/addons/github_connector/models/github.py
odoo/addons/github_connector/models/github_organization.py
odoo/addons/github_connector/models/github_organization_serie.py
odoo/addons/github_connector/models/github_repository.py
odoo/addons/github_connector/models/github_repository_branch.py
odoo/addons/github_connector/models/github_team.py
odoo/addons/github_connector/models/github_team_partner.py
odoo/addons/github_connector/models/github_team_repository.py
odoo/addons/github_connector/models/ir_values.py
odoo/addons/github_connector/models/res_partner.py
odoo/addons/github_connector/models/wizard_create_repository.py
odoo/addons/github_connector/models/wizard_create_team.py
odoo/addons/github_connector/models/wizard_download_analyze_branch.py
odoo/addons/github_connector/models/wizard_load_github_model.py
odoo/addons/github_connector/models/wizard_update_branch_list.py
odoo/addons/github_connector/models/wizard_update_from_github.py
odoo/addons/github_connector/security/ir.model.access.csv
odoo/addons/github_connector/security/ir_model_category.xml
odoo/addons/github_connector/security/res_groups.xml
odoo/addons/github_connector/static/description/github_organization_external_services.png
odoo/addons/github_connector/static/description/github_organization_kanban.png
odoo/addons/github_connector/static/description/github_organization_series.png
odoo10_addon_github_connector-10.0.1.0.0.99.dev25.dist-info/DESCRIPTION.rst
odoo10_addon_github_connector-10.0.1.0.0.99.dev25.dist-info/METADATA
odoo10_addon_github_connector-10.0.1.0.0.99.dev25.dist-info/RECORD
odoo10_addon_github_connector-10.0.1.0.0.99.dev25.dist-info/WHEEL
odoo10_addon_github_connector-10.0.1.0.0.99.dev25.dist-info/metadata.json
odoo10_addon_github_connector-10.0.1.0.0.99.dev25.dist-info/namespace_packages.txt
odoo10_addon_github_connector-10.0.1.0.0.99.dev25.dist-info/top_level.txt
